{
  "基础服务": {
    "desc": "绑定用户信息",
    "data": [
      {
        "name": "绑定uid",
        "desc": "绑定uid",
        "eg": "绑定uid123456",
        "need_ck": false,
        "need_sk": false,
        "need_admin": false
      },
	  {
        "name": "QQ登录",
        "desc": "QQ扫码登录",
        "eg": "QQ登录",
        "need_ck": true,
        "need_sk": true,
        "need_admin": false
      },
	  {
        "name": "洛克档案",
        "desc": "洛克档案",
        "eg": "洛克档案/rcuid",
        "need_ck": true,
        "need_sk": true,
        "need_admin": false
      }
    ]
  },
  "查询推送服务": {
    "desc": "查询推送服务",
    "data": [
      {
        "name": "远行商人",
        "desc": "远行商人",
        "eg": "远行商人",
        "need_ck": false,
        "need_sk": true,
        "need_admin": false
      },
	  {
        "name": "远行商人推送",
        "desc": "[开启/关闭]远行商人",
        "eg": "[开启/关闭]远行商人",
        "need_ck": false,
        "need_sk": true,
        "need_admin": false
      },
	  {
        "name": "家园",
        "desc": "家园",
        "eg": "家园[UID]",
        "need_ck": false,
        "need_sk": true,
        "need_admin": false
      },
	  {
        "name": "刷新面板",
        "desc": "刷新面板",
        "eg": "刷新面板[UID]",
        "need_ck": false,
        "need_sk": true,
        "need_admin": false
      },
	  {
        "name": "查询",
        "desc": "查询",
        "eg": "查询[ID/昵称][UID]",
        "need_ck": false,
        "need_sk": true,
        "need_admin": false
      }
    ]
  },
  "图鉴服务": {
    "desc": "查询精灵信息",
    "data": [
      {
        "name": "图鉴",
        "desc": "查询精灵图鉴",
        "eg": "图鉴迪莫",
        "need_ck": false,
        "need_sk": false,
        "need_admin": false
      },
	  {
        "name": "技能信息",
        "desc": "查询技能信息",
        "eg": "技能信息抓挠",
        "need_ck": false,
        "need_sk": false,
        "need_admin": false
      },
	  {
        "name": "配种",
        "desc": "查询配种情况",
        "eg": "配种[母精灵][父精灵]",
        "need_ck": false,
        "need_sk": false,
        "need_admin": false
      },
	  {
        "name": "查找精灵",
        "desc": "条件查找精灵",
        "eg": "查找精灵 技能,折射,黑手",
        "need_ck": false,
        "need_sk": false,
        "need_admin": false
      },
	  {
        "name": "精灵蛋/查蛋",
        "desc": "查找精灵蛋信息",
        "eg": "查蛋[尺寸][重量]",
        "need_ck": false,
        "need_sk": false,
        "need_admin": false
      }
    ]
  }
}
